azure/servicebus/__init__.py
azure/servicebus/_base_handler.py
azure/servicebus/_servicebus_client.py
azure/servicebus/_servicebus_receiver.py
azure/servicebus/_servicebus_sender.py
azure/servicebus/_servicebus_session.py
azure/servicebus/_version.py
azure/servicebus/exceptions.py
azure/servicebus/py.typed
azure/servicebus/_common/__init__.py
azure/servicebus/_common/_configuration.py
azure/servicebus/_common/_connection_string_parser.py
azure/servicebus/_common/auto_lock_renewer.py
azure/servicebus/_common/constants.py
azure/servicebus/_common/message.py
azure/servicebus/_common/mgmt_handlers.py
azure/servicebus/_common/receiver_mixins.py
azure/servicebus/_common/tracing.py
azure/servicebus/_common/utils.py
azure/servicebus/_pyamqp/__init__.py
azure/servicebus/_pyamqp/_connection.py
azure/servicebus/_pyamqp/_decode.py
azure/servicebus/_pyamqp/_encode.py
azure/servicebus/_pyamqp/_message_backcompat.py
azure/servicebus/_pyamqp/_platform.py
azure/servicebus/_pyamqp/_transport.py
azure/servicebus/_pyamqp/authentication.py
azure/servicebus/_pyamqp/cbs.py
azure/servicebus/_pyamqp/client.py
azure/servicebus/_pyamqp/constants.py
azure/servicebus/_pyamqp/endpoints.py
azure/servicebus/_pyamqp/error.py
azure/servicebus/_pyamqp/link.py
azure/servicebus/_pyamqp/management_link.py
azure/servicebus/_pyamqp/management_operation.py
azure/servicebus/_pyamqp/message.py
azure/servicebus/_pyamqp/outcomes.py
azure/servicebus/_pyamqp/performatives.py
azure/servicebus/_pyamqp/receiver.py
azure/servicebus/_pyamqp/sasl.py
azure/servicebus/_pyamqp/sender.py
azure/servicebus/_pyamqp/session.py
azure/servicebus/_pyamqp/types.py
azure/servicebus/_pyamqp/utils.py
azure/servicebus/_pyamqp/aio/__init__.py
azure/servicebus/_pyamqp/aio/_authentication_async.py
azure/servicebus/_pyamqp/aio/_cbs_async.py
azure/servicebus/_pyamqp/aio/_client_async.py
azure/servicebus/_pyamqp/aio/_connection_async.py
azure/servicebus/_pyamqp/aio/_link_async.py
azure/servicebus/_pyamqp/aio/_management_link_async.py
azure_servicebus-7.14.1.dist-info/LICENSE
azure_servicebus-7.14.1.dist-info/METADATA
azure_servicebus-7.14.1.dist-info/WHEEL
azure_servicebus-7.14.1.dist-info/top_level.txt
azure_servicebus-7.14.1.dist-info/RECORD
